{
    "CreationDate": "2017-Aug-25",
    "DEC": 2.527777164070965e-06,
    "NHI": 0.0,
    "Name": "J000000.0015+000000.0091_z0.143",
    "RA": 6.3611113549858365e-06,
    "Refs": [],
    "ZH": 0.0,
    "abs_type": "Generic",
    "class": "GenericAbsSystem",
    "components": {
        "CaII_z0.14290": {
            "A": null,
            "DEC": 2.527777164070965e-06,
            "Ej": 0.0,
            "Name": "CaII_z0.14290",
            "RA": 6.3611113549858365e-06,
            "Zion": [
                20,
                2
            ],
            "class": "AbsComponent",
            "comment": "",
            "flag_N": 0,
            "lines": {
                "3934.777": {
                    "analy": {
                        "datafile": "n_GOTOQJ1241+6332a_F.fits",
                        "do_analysis": 1,
                        "flag_kin": 0,
                        "flg_eye": 0,
                        "flg_limit": 0,
                        "name": "CaII 3934"
                    },
                    "attrib": {
                        "DEC": 0.0,
                        "EW": {
                            "unit": "Angstrom",
                            "value": 0.0
                        },
                        "N": {
                            "unit": "1 / cm2",
                            "value": 0.0
                        },
                        "RA": 0.0,
                        "b": {
                            "unit": "km / s",
                            "value": 0.0
                        },
                        "flag_EW": 0,
                        "flag_N": 0,
                        "logN": 0.0,
                        "sig_EW": {
                            "unit": "Angstrom",
                            "value": 0.0
                        },
                        "sig_N": {
                            "unit": "1 / cm2",
                            "value": 0.0
                        },
                        "sig_b": {
                            "unit": "km / s",
                            "value": 0.0
                        },
                        "sig_logN": 0.0
                    },
                    "data": {
                        "A": {
                            "unit": "1 / s",
                            "value": 0.0
                        },
                        "Am": 0,
                        "Ej": {
                            "unit": "1 / cm",
                            "value": 0.0
                        },
                        "Ek": {
                            "unit": "1 / cm",
                            "value": 0.0
                        },
                        "Ex": {
                            "unit": "1 / cm",
                            "value": 0.0
                        },
                        "Jj": 0.0,
                        "Jk": 0.0,
                        "Ref": "Verner1994",
                        "Z": 20,
                        "abundance": 6.29,
                        "el": 0,
                        "f": 0.6499999761581421,
                        "gamma": {
                            "unit": "1 / s",
                            "value": 0.0
                        },
                        "gj": 2,
                        "gk": 4,
                        "group": 1,
                        "ion": 2,
                        "ion_correction": 0.0,
                        "ion_name": "CaII",
                        "is_EUV": false,
                        "is_HI": false,
                        "is_Strong": true,
                        "log(w*f)": 3.407833464850605,
                        "mol": "",
                        "name": "CaII 3934",
                        "nj": 0,
                        "nk": 0,
                        "rel_strength": 9.697833464850605,
                        "wrest": {
                            "unit": "Angstrom",
                            "value": 3934.777
                        }
                    },
                    "limits": {
                        "vlim": {
                            "unit": "km / s",
                            "value": [
                                -150.0000000000023,
                                150.00000000005048
                            ]
                        },
                        "wrest": {
                            "unit": "Angstrom",
                            "value": 3934.777
                        },
                        "wvlim": {
                            "unit": "Angstrom",
                            "value": [
                                4494.807110988703,
                                4499.30728143283
                            ]
                        },
                        "z": 0.1429,
                        "zlim": [
                            0.14232829738221597,
                            0.1434719887385815
                        ]
                    },
                    "ltype": "Abs",
                    "name": "CaII 3934",
                    "wrest": {
                        "unit": "Angstrom",
                        "value": 3934.777
                    }
                },
                "3969.591": {
                    "analy": {
                        "datafile": "n_GOTOQJ1241+6332a_F.fits",
                        "do_analysis": 1,
                        "flag_kin": 0,
                        "flg_eye": 0,
                        "flg_limit": 0,
                        "name": "CaII 3969"
                    },
                    "attrib": {
                        "DEC": 0.0,
                        "EW": {
                            "unit": "Angstrom",
                            "value": 0.0
                        },
                        "N": {
                            "unit": "1 / cm2",
                            "value": 0.0
                        },
                        "RA": 0.0,
                        "b": {
                            "unit": "km / s",
                            "value": 0.0
                        },
                        "flag_EW": 0,
                        "flag_N": 0,
                        "logN": 0.0,
                        "sig_EW": {
                            "unit": "Angstrom",
                            "value": 0.0
                        },
                        "sig_N": {
                            "unit": "1 / cm2",
                            "value": 0.0
                        },
                        "sig_b": {
                            "unit": "km / s",
                            "value": 0.0
                        },
                        "sig_logN": 0.0
                    },
                    "data": {
                        "A": {
                            "unit": "1 / s",
                            "value": 0.0
                        },
                        "Am": 0,
                        "Ej": {
                            "unit": "1 / cm",
                            "value": 0.0
                        },
                        "Ek": {
                            "unit": "1 / cm",
                            "value": 0.0
                        },
                        "Ex": {
                            "unit": "1 / cm",
                            "value": 0.0
                        },
                        "Jj": 0.0,
                        "Jk": 0.0,
                        "Ref": "Verner1994",
                        "Z": 20,
                        "abundance": 6.29,
                        "el": 0,
                        "f": 0.32199999690055847,
                        "gamma": {
                            "unit": "1 / s",
                            "value": 0.0
                        },
                        "gj": 2,
                        "gk": 2,
                        "group": 1,
                        "ion": 2,
                        "ion_correction": 0.0,
                        "ion_name": "CaII",
                        "is_EUV": false,
                        "is_HI": false,
                        "is_Strong": true,
                        "log(w*f)": 3.1066016297966126,
                        "mol": "",
                        "name": "CaII 3969",
                        "nj": 0,
                        "nk": 0,
                        "rel_strength": 9.396601629796614,
                        "wrest": {
                            "unit": "Angstrom",
                            "value": 3969.591
                        }
                    },
                    "limits": {
                        "vlim": {
                            "unit": "km / s",
                            "value": [
                                -150.0000000000023,
                                150.00000000005048
                            ]
                        },
                        "wrest": {
                            "unit": "Angstrom",
                            "value": 3969.591
                        },
                        "wvlim": {
                            "unit": "Angstrom",
                            "value": [
                                4534.576128333768,
                                4539.116115248775
                            ]
                        },
                        "z": 0.1429,
                        "zlim": [
                            0.14232829738221597,
                            0.1434719887385815
                        ]
                    },
                    "ltype": "Abs",
                    "name": "CaII 3969",
                    "wrest": {
                        "unit": "Angstrom",
                        "value": 3969.591
                    }
                }
            },
            "logN": 0.0,
            "sig_logN": 0.0,
            "vlim": [
                -150.0000000000023,
                150.00000000005048
            ],
            "zcomp": 0.1429
        },
        "NaI_z0.14290": {
            "A": null,
            "DEC": 2.527777164070965e-06,
            "Ej": 0.0,
            "Name": "NaI_z0.14290",
            "RA": 6.3611113549858365e-06,
            "Zion": [
                11,
                1
            ],
            "class": "AbsComponent",
            "comment": "",
            "flag_N": 0,
            "lines": {
                "5891.5833": {
                    "analy": {
                        "datafile": "n_GOTOQJ1241+6332a_F.fits",
                        "do_analysis": 1,
                        "flag_kin": 0,
                        "flg_eye": 0,
                        "flg_limit": 0,
                        "name": "NaI  5891"
                    },
                    "attrib": {
                        "DEC": 0.0,
                        "EW": {
                            "unit": "Angstrom",
                            "value": 0.0
                        },
                        "N": {
                            "unit": "1 / cm2",
                            "value": 0.0
                        },
                        "RA": 0.0,
                        "b": {
                            "unit": "km / s",
                            "value": 0.0
                        },
                        "flag_EW": 0,
                        "flag_N": 0,
                        "logN": 0.0,
                        "sig_EW": {
                            "unit": "Angstrom",
                            "value": 0.0
                        },
                        "sig_N": {
                            "unit": "1 / cm2",
                            "value": 0.0
                        },
                        "sig_b": {
                            "unit": "km / s",
                            "value": 0.0
                        },
                        "sig_logN": 0.0
                    },
                    "data": {
                        "A": {
                            "unit": "1 / s",
                            "value": 61570000.0
                        },
                        "Am": 0,
                        "Ej": {
                            "unit": "1 / cm",
                            "value": 0.0
                        },
                        "Ek": {
                            "unit": "1 / cm",
                            "value": 6973.36616
                        },
                        "Ex": {
                            "unit": "1 / cm",
                            "value": 0.0
                        },
                        "Jj": 0.0,
                        "Jk": 0.0,
                        "Ref": "Morton2003",
                        "Z": 11,
                        "abundance": 6.27,
                        "el": 0,
                        "f": 0.6408,
                        "gamma": {
                            "unit": "1 / s",
                            "value": 61570000.0
                        },
                        "gj": 2,
                        "gk": 4,
                        "group": 1,
                        "ion": 1,
                        "ion_correction": 0.0,
                        "ion_name": "NaI",
                        "is_EUV": false,
                        "is_HI": false,
                        "is_Strong": true,
                        "log(w*f)": 3.576954525545773,
                        "mol": "",
                        "name": "NaI  5891",
                        "nj": 0,
                        "nk": 0,
                        "rel_strength": 9.846954525545772,
                        "wrest": {
                            "unit": "Angstrom",
                            "value": 5891.5833
                        }
                    },
                    "limits": {
                        "vlim": {
                            "unit": "km / s",
                            "value": [
                                -150.0000000000023,
                                150.00000000005048
                            ]
                        },
                        "wrest": {
                            "unit": "Angstrom",
                            "value": 5891.5833
                        },
                        "wvlim": {
                            "unit": "Angstrom",
                            "value": [
                                6730.122319974497,
                                6736.860472870016
                            ]
                        },
                        "z": 0.1429,
                        "zlim": [
                            0.14232829738221597,
                            0.1434719887385815
                        ]
                    },
                    "ltype": "Abs",
                    "name": "NaI  5891",
                    "wrest": {
                        "unit": "Angstrom",
                        "value": 5891.5833
                    }
                },
                "5897.5581": {
                    "analy": {
                        "datafile": "n_GOTOQJ1241+6332a_F.fits",
                        "do_analysis": 1,
                        "flag_kin": 0,
                        "flg_eye": 0,
                        "flg_limit": 0,
                        "name": "NaI  5897"
                    },
                    "attrib": {
                        "DEC": 0.0,
                        "EW": {
                            "unit": "Angstrom",
                            "value": 0.0
                        },
                        "N": {
                            "unit": "1 / cm2",
                            "value": 0.0
                        },
                        "RA": 0.0,
                        "b": {
                            "unit": "km / s",
                            "value": 0.0
                        },
                        "flag_EW": 0,
                        "flag_N": 0,
                        "logN": 0.0,
                        "sig_EW": {
                            "unit": "Angstrom",
                            "value": 0.0
                        },
                        "sig_N": {
                            "unit": "1 / cm2",
                            "value": 0.0
                        },
                        "sig_b": {
                            "unit": "km / s",
                            "value": 0.0
                        },
                        "sig_logN": 0.0
                    },
                    "data": {
                        "A": {
                            "unit": "1 / s",
                            "value": 61390000.0
                        },
                        "Am": 0,
                        "Ej": {
                            "unit": "1 / cm",
                            "value": 0.0
                        },
                        "Ek": {
                            "unit": "1 / cm",
                            "value": 6956.17025
                        },
                        "Ex": {
                            "unit": "1 / cm",
                            "value": 0.0
                        },
                        "Jj": 0.0,
                        "Jk": 0.0,
                        "Ref": "Morton2003",
                        "Z": 11,
                        "abundance": 6.27,
                        "el": 0,
                        "f": 0.3201,
                        "gamma": {
                            "unit": "1 / s",
                            "value": 61390000.0
                        },
                        "gj": 2,
                        "gk": 2,
                        "group": 1,
                        "ion": 1,
                        "ion_correction": 0.0,
                        "ion_name": "NaI",
                        "is_EUV": false,
                        "is_HI": false,
                        "is_Strong": true,
                        "log(w*f)": 3.275957902190126,
                        "mol": "",
                        "name": "NaI  5897",
                        "nj": 0,
                        "nk": 0,
                        "rel_strength": 9.545957902190125,
                        "wrest": {
                            "unit": "Angstrom",
                            "value": 5897.5581
                        }
                    },
                    "limits": {
                        "vlim": {
                            "unit": "km / s",
                            "value": [
                                -150.0000000000023,
                                49.777703493226625
                            ]
                        },
                        "wrest": {
                            "unit": "Angstrom",
                            "value": 5897.5581
                        },
                        "wvlim": {
                            "unit": "Angstrom",
                            "value": [
                                6736.947503085697,
                                6741.438411693017
                            ]
                        },
                        "z": 0.1429,
                        "zlim": [
                            0.14232829738221597,
                            0.14308978349751508
                        ]
                    },
                    "ltype": "Abs",
                    "name": "NaI  5897",
                    "wrest": {
                        "unit": "Angstrom",
                        "value": 5897.5581
                    }
                }
            },
            "logN": 0.0,
            "sig_logN": 0.0,
            "vlim": [
                -150.0000000000023,
                150.00000000005048
            ],
            "zcomp": 0.1429
        }
    },
    "flag_NHI": 0,
    "flag_ZH": 0,
    "kin": {},
    "sig_NHI": [
        0.0,
        0.0
    ],
    "sig_ZH": 0.0,
    "user": "ryan",
    "vlim": [
        -300.0,
        300.0
    ],
    "zabs": 0.1429,
    "zem": 0.0
}